scrapy_save_statistics/__init__.py
scrapy_save_statistics/savestatistics.py
scrapy_save_statistics-0.2.dist-info/DESCRIPTION.rst
scrapy_save_statistics-0.2.dist-info/METADATA
scrapy_save_statistics-0.2.dist-info/RECORD
scrapy_save_statistics-0.2.dist-info/WHEEL
scrapy_save_statistics-0.2.dist-info/metadata.json
scrapy_save_statistics-0.2.dist-info/top_level.txt
