Metadata-Version: 2.0
Name: scrapy-save-statistics
Version: 0.2
Summary: Scrapy Save Statistics: Save statistics extension for Scrapy
Home-page: https://github.com/light4/scrapy-save-statistics
Author: Light Ning
Author-email: lightning1141@gmail.com
License: MIT
Platform: UNKNOWN
Classifier: Development Status :: 3 - Alpha
Classifier: Intended Audience :: Developers
Classifier: Topic :: Internet :: WWW/HTTP
Classifier: License :: OSI Approved :: MIT License
Classifier: Programming Language :: Python :: 2
Classifier: Programming Language :: Python :: 2.7
Classifier: Programming Language :: Python :: 3
Classifier: Programming Language :: Python :: 3.5
Classifier: Programming Language :: Python :: 3.6
Requires-Dist: Scrapy (>=1.0)
